{
  "GuideData": {
    "AdsController": [
      {
        "NetworkAds": "applovin",
        "AdMobId": "pub-3940256099942544",
        "BannerAdmob": "ca-app-pub-3940256099942544/6300978111",
        "InterstitialAdmob": "ca-app-pub-3940256099942544/1033173712",
        "NativeAdmob": "ca-app-pub-3940256099942544/2247696110",
        "SDKKEYAppLovin": "MRQ6wu7Or0GoeHcIXLPNCxnsPNMTnTfRCzkKik91TITN6xGsTDnXQ9vbv-8RggawlzwcdwiU0e5izkq0swvImE",
        "BannerAppLovin": "868d73d31ebd3fe5",
        "InterstitialAppLovin": "88ac61ac8b1c81b0",
        "MRECAppLovin": "162685d11bac5cde",
        "RewardAppLovin": "ac7aeca2eebee147"
      }
    ],
    "items": [
      {
        "title": "Main Quests",
        "image": "https://i.ytimg.com/vi/T99xvT_Hl9s/maxresdefault.jpg"
      },
      {
        "title": "A Hidden Path",
        "image": "https://i.ytimg.com/vi/u3Zru5dGQR0/maxresdefault.jpg"
      },
      {
        "title": "Rodia Town",
        "image": "https://i.ytimg.com/vi/T99xvT_Hl9s/maxresdefault.jpg"
      },
      {
        "title": "Find Ranotto the Minstrel",
        "image": "https://i.ytimg.com/vi/u3Zru5dGQR0/maxresdefault.jpg"
      },
      {
        "title": "Cosetta the Lost Dog",
        "image": "https://i.ytimg.com/vi/T99xvT_Hl9s/maxresdefault.jpg"
      },
      {
        "title": "Savoca Prison",
        "image": "https://i.ytimg.com/vi/u3Zru5dGQR0/maxresdefault.jpg"
      }
    ],
    "content1": [
      {
        "ordered": "image_text",
        "color": "#FFFFFF",
        "style": "blood",
        "gravity": "left",
        "left": "10",
        "text_size": "20",
        "isLink": "false",
        "link_title": "",
        "setLink": "",
        "image_link": "",
        "text": "Its your process to ensure no person robs Mr Funny's ToyShop,and It's important to preserve the energy offThe factory appears to encounter ,When the Power is grew to become on in the course of the Night shift.",
        "isNative": "false"
      },
      {
        "ordered": "image_text",
        "color": "#f56342",
        "style": "blood",
        "gravity": "left",
        "left": "10",
        "text_size": "25",
        "isLink": "false",
        "link_title": "",
        "setLink": "",
        "image_link": "",
        "text": "Escape Mr Funny's ToyShop",
        "isNative": "false"
      },
      {
        "ordered": "image_text",
        "color": "#FFFFFF",
        "style": "blood",
        "gravity": "left",
        "left": "10",
        "text_size": "25",
        "isLink": "false",
        "link_title": "",
        "setLink": "",
        "image_link": "",
        "text": "Make your manner via the Factory and ensure to keep away from the scary obby and Mr Funny Dummy that lurks withinside the darkness.",
        "isNative": "true"
      },
      {
        "ordered": "image_text",
        "color": "#f56342",
        "style": "blood",
        "gravity": "left",
        "left": "10",
        "text_size": "25",
        "isLink": "false",
        "link_title": "",
        "setLink": "",
        "image_link": "",
        "text": "Escape Mr Funny's ToyShop",
        "isNative": "false"
      },
      {
        "ordered": "image_text",
        "color": "#FFFFFF",
        "style": "blood",
        "gravity": "left",
        "left": "10",
        "text_size": "25",
        "isLink": "false",
        "link_title": "",
        "setLink": "",
        "image_link": "",
        "text": "Its your job to make sure no one robs the place, Also.. It's important to keep the power OFF! The factory seems to encounter....Problems?...When the Power is turned on during the Night shift.",
        "isNative": "true"
      },
      {
        "ordered": "image_text",
        "color": "#FFFFFF",
        "style": "blood",
        "gravity": "left",
        "left": "10",
        "text_size": "25",
        "isLink": "false",
        "link_title": "",
        "setLink": "",
        "image_link": "",
        "text": "Make your way through the Factory and make sure to avoid the Mr Funny Dummy that lurks in the darkness.",
        "isNative": "false"
      },
      {
        "ordered": "image_text",
        "color": "#f56342",
        "style": "blood",
        "gravity": "left",
        "left": "10",
        "text_size": "25",
        "isLink": "false",
        "link_title": "",
        "setLink": "",
        "image_link": "",
        "text": "Just sit back, Relax and make sure not to turn on the power BUT..",
        "isNative": "false"
      },
      {
        "ordered": "image_text",
        "color": "#FFFFFF",
        "style": "blood",
        "gravity": "left",
        "left": "10",
        "text_size": "25",
        "isLink": "false",
        "link_title": "",
        "setLink": "",
        "image_link": "",
        "text": "hello everyone, welcome to the best game of all fans Mr Funny's ToyShop! game for scary obby.",
        "isNative": "true"
      }
    ],
    "content2": [
      {
        "ordered": "image_text",
        "color": "#f56342",
        "style": "blood",
        "gravity": "left",
        "left": "10",
        "text_size": "25",
        "isLink": "false",
        "link_title": "",
        "setLink": "",
        "image_link": "",
        "text": "Escape Mr Funny's ToyShop",
        "isNative": "false"
      },
      {
        "ordered": "image_text",
        "color": "#FFFFFF",
        "style": "blood",
        "gravity": "left",
        "left": "10",
        "text_size": "25",
        "isLink": "false",
        "link_title": "",
        "setLink": "",
        "image_link": "",
        "text": "This 3D multiplayer worm slink game is part of .io games family. Now, this awesome worm game has upgraded gameplay.",
        "isNative": "true"
      },
      {
        "ordered": "image_text",
        "color": "#f56342",
        "style": "blood",
        "gravity": "left",
        "left": "10",
        "text_size": "25",
        "isLink": "false",
        "link_title": "",
        "setLink": "",
        "image_link": "",
        "text": "Escape Mr Funny's ToyShop",
        "isNative": "false"
      },
      {
        "ordered": "image_text",
        "color": "#FFFFFF",
        "style": "blood",
        "gravity": "left",
        "left": "10",
        "text_size": "25",
        "isLink": "false",
        "link_title": "",
        "setLink": "",
        "image_link": "",
        "text": "This New game scary obby is funny So its your first day as a Security guard for Mr Funny's ToyShop.The story is about a Mr Funny Dummy that lurks in the darkness.",
        "isNative": "false"
      }
    ],
    "content3": [
      {
        "ordered": "image_text",
        "color": "#f56342",
        "style": "blood",
        "gravity": "left",
        "left": "10",
        "text_size": "25",
        "isLink": "false",
        "link_title": "",
        "setLink": "",
        "image_link": "",
        "text": "Escape Mr Funny's ToyShop",
        "isNative": "false"
      },
      {
        "ordered": "image_text",
        "color": "#FFFFFF",
        "style": "blood",
        "gravity": "left",
        "left": "10",
        "text_size": "25",
        "isLink": "false",
        "link_title": "",
        "setLink": "",
        "image_link": "",
        "text": "ts your job to make sure no one robs the place, Also.. It's important to keep the power OFF! The factory seems to",
        "isNative": "false"
      },
      {
        "ordered": "image_text",
        "color": "#FFFFFF",
        "style": "blood",
        "gravity": "left",
        "left": "10",
        "text_size": "25",
        "isLink": "false",
        "link_title": "",
        "setLink": "",
        "image_link": "",
        "text": "Similar to a classic action game",
        "isNative": "false"
      },
      {
        "ordered": "image_text",
        "color": "#FFFFFF",
        "style": "blood",
        "gravity": "left",
        "left": "10",
        "text_size": "25",
        "isLink": "false",
        "link_title": "",
        "setLink": "",
        "image_link": "",
        "text": "Mr Funny's ToyShop",
        "isNative": "false"
      }
    ],
    "content4": [
      {
        "ordered": "image_text",
        "color": "#f56342",
        "style": "blood",
        "gravity": "left",
        "left": "10",
        "text_size": "25",
        "isLink": "false",
        "link_title": "",
        "setLink": "",
        "image_link": "",
        "text": "Escape Mr Funny's ToyShop",
        "isNative": "false"
      },
      {
        "ordered": "image_text",
        "color": "#FFFFFF",
        "style": "blood",
        "gravity": "left",
        "left": "10",
        "text_size": "25",
        "isLink": "false",
        "link_title": "",
        "setLink": "",
        "image_link": "",
        "text": "What’s the ideal revenge? Just sit back, Relax and make sure not to turn on the power BUT..Lets say you do turn it on and need to escape well",
        "isNative": "false"
      },
      {
        "ordered": "image_text",
        "color": "#FFFFFF",
        "style": "blood",
        "gravity": "left",
        "left": "10",
        "text_size": "25",
        "isLink": "false",
        "link_title": "",
        "setLink": "",
        "image_link": "",
        "text": "Hit other worms by sneaking and encircling them into your worm's body cleverly.",
        "isNative": "false"
      },
      {
        "ordered": "image_text",
        "color": "#FFFFFF",
        "style": "blood",
        "gravity": "left",
        "left": "10",
        "text_size": "25",
        "isLink": "false",
        "link_title": "",
        "setLink": "",
        "image_link": "",
        "text": "Make your way through the Factory and make sure to avoid the Mr Funny Dummy in Escape Mr Funny's ToyShop.",
        "isNative": "false"
      }
    ],
    "content5": [
      {
        "ordered": "image_text",
        "color": "#f56342",
        "style": "blood",
        "gravity": "left",
        "left": "10",
        "text_size": "25",
        "isLink": "false",
        "link_title": "",
        "setLink": "",
        "image_link": "",
        "text": "Snake io worms zone",
        "isNative": "false"
      },
      {
        "ordered": "image_text",
        "color": "#FFFFFF",
        "style": "blood",
        "gravity": "left",
        "left": "10",
        "text_size": "25",
        "isLink": "false",
        "link_title": "",
        "setLink": "",
        "image_link": "",
        "text": "This is an official port of the original game with touch screen controls and controller support! Check out the options menu to adjust these features to your liking",
        "isNative": "false"
      },
      {
        "ordered": "image_text",
        "color": "#FFFFFF",
        "style": "blood",
        "gravity": "left",
        "left": "10",
        "text_size": "25",
        "isLink": "false",
        "link_title": "",
        "setLink": "",
        "image_link": "",
        "text": "Make your way through the Factory and make sure to avoid the Mr Funny Dummy in Escape Mr",
        "isNative": "false"
      },
      {
        "ordered": "image_text",
        "color": "#FFFFFF",
        "style": "blood",
        "gravity": "left",
        "left": "10",
        "text_size": "25",
        "isLink": "false",
        "link_title": "",
        "setLink": "",
        "image_link": "",
        "text": "Travel through the 15 crazy rooms Obstacles and mini games that await you."
        "isNative": "false"
      }
    ],
    "content6": [
      {
        "ordered": "image_text",
        "color": "#f56342",
        "style": "blood",
        "gravity": "left",
        "left": "10",
        "text_size": "25",
        "isLink": "false",
        "link_title": "",
        "setLink": "",
        "image_link": "",
        "text": "Escape Mr Funny's ToyShop!",
        "isNative": "false"
      },
      {
        "ordered": "image_text",
        "color": "#FFFFFF",
        "style": "blood",
        "gravity": "left",
        "left": "10",
        "text_size": "25",
        "isLink": "false",
        "link_title": "",
        "setLink": "",
        "image_link": "",
        "text": "Make your way through the Factory and make sure to avoid the Mr Funny Dummy in Escape Mr",
        "isNative": "false"
      },
      {
        "ordered": "image_text",
        "color": "#FFFFFF",
        "style": "blood",
        "gravity": "left",
        "left": "10",
        "text_size": "25",
        "isLink": "false",
        "link_title": "",
        "setLink": "",
        "image_link": "",
        "text": "Travel through the crazy rooms Obstacles and mini games that await you.",
        "isNative": "false"
      },
      {
        "ordered": "image_text",
        "color": "#FFFFFF",
        "style": "blood",
        "gravity": "left",
        "left": "10",
        "text_size": "25",
        "isLink": "false",
        "link_title": "",
        "setLink": "",
        "image_link": "",
        "text": "What’s the ideal revenge Just sit back, Relax and make sure not to turn on the power BUT..",
        "isNative": "false"
      }
    ],
    "content7": [
      {
        "ordered": "image_text",
        "color": "#f56342",
        "style": "blood",
        "gravity": "left",
        "left": "10",
        "text_size": "25",
        "isLink": "false",
        "link_title": "",
        "setLink": "",
        "image_link": "",
        "text": "Escape Mr Funny's ToyShop",
        "isNative": "false"
      },
      {
        "ordered": "image_text",
        "color": "#FFFFFF",
        "style": "blood",
        "gravity": "left",
        "left": "10",
        "text_size": "25",
        "isLink": "false",
        "link_title": "",
        "setLink": "",
        "image_link": "",
        "text": "Make your way through the Factory and make sure to avoid the Mr Funny Dummy in Escape Mr Funny's ToyShop.",
        "isNative": "false"
      },
      {
        "ordered": "image_text",
        "color": "#FFFFFF",
        "style": "blood",
        "gravity": "left",
        "left": "10",
        "text_size": "25",
        "isLink": "false",
        "link_title": "",
        "setLink": "",
        "image_link": "",
        "text": "Lets say you do turn it on and need to escape well",
        "isNative": "false"
      },
      {
        "ordered": "image_text",
        "color": "#FFFFFF",
        "style": "blood",
        "gravity": "left",
        "left": "10",
        "text_size": "25",
        "isLink": "false",
        "link_title": "",
        "setLink": "",
        "image_link": "",
        "text": "This is an official port of the original game with touch screen controls and controller support! Check out the options menu to adjust these features to your liking!",
        "isNative": "false"
      }
    ]
  }
}
